fatamorgana/LICENSE.md
fatamorgana/README.md
fatamorgana/__init__.py
fatamorgana/basic.py
fatamorgana/main.py
fatamorgana/py.typed
fatamorgana/records.py
fatamorgana/test/__init__.py
fatamorgana/test/build_testfiles.py
fatamorgana/test/test_files_cblocks.py
fatamorgana/test/test_files_cells.py
fatamorgana/test/test_files_circles.py
fatamorgana/test/test_files_ctrapezoids.py
fatamorgana/test/test_files_empty.py
fatamorgana/test/test_files_layernames.py
fatamorgana/test/test_files_modals.py
fatamorgana/test/test_files_paths.py
fatamorgana/test/test_files_placements.py
fatamorgana/test/test_files_polygons.py
fatamorgana/test/test_files_properties.py
fatamorgana/test/test_files_rectangles.py
fatamorgana/test/test_files_texts.py
fatamorgana/test/test_files_trapezoids.py
fatamorgana/test/test_int.py
fatamorgana/test/utils.py
fatamorgana-0.13.dist-info/METADATA
fatamorgana-0.13.dist-info/WHEEL
fatamorgana-0.13.dist-info/licenses/LICENSE.md
fatamorgana-0.13.dist-info/RECORD
