Metadata-Version: 2.3
Name: fatamorgana
Version: 0.13
Summary: OASIS layout format parser and writer
Author-email: Jan Petykiewicz <jan@mpxd.net>
License: GNU Affero General Public License
License-File: LICENSE.md
Keywords: CAD,EDA,IC,OASIS,artwork,design,electronics,gds,geometric,geometry,interchange,layout,mask,oas,open,pattern,polygon,standard
Classifier: Development Status :: 3 - Alpha
Classifier: Environment :: Other Environment
Classifier: Intended Audience :: Developers
Classifier: Intended Audience :: Information Technology
Classifier: Intended Audience :: Manufacturing
Classifier: Intended Audience :: Science/Research
Classifier: License :: OSI Approved :: GNU Affero General Public License v3
Classifier: Programming Language :: Python :: 3
Classifier: Topic :: Scientific/Engineering
Classifier: Topic :: Scientific/Engineering :: Electronic Design Automation (EDA)
Requires-Python: >=3.11
Provides-Extra: numpy
Requires-Dist: numpy>=1.26; extra == 'numpy'
